irrigation_calc/__init__.py
irrigation_calc-0.0.1.dist-info/LICENSE
irrigation_calc-0.0.1.dist-info/METADATA
irrigation_calc-0.0.1.dist-info/WHEEL
irrigation_calc-0.0.1.dist-info/top_level.txt
irrigation_calc-0.0.1.dist-info/RECORD
